codefest/cf04/hdl/mac_correct.v
// mac_correct.v
// Correct synthesizable SystemVerilog MAC unit
// Model: Claude Sonnet 4.6

module mac (
    input  logic        clk,
    input  logic        rst,
    input  logic signed [7:0]  a,
    input  logic signed [7:0]  b,
    output logic signed [31:0] out
);

    logic signed [15:0] product;
    logic signed [31:0] product_ext;

    always_ff @(posedge clk) begin
        if (rst) begin
            out <= 32'sd0;
        end else begin
            product     = a * b;                          // 16-bit signed multiply
            product_ext = {{16{product[15]}}, product};   // explicit sign-extend to 32-bit
            out         <= out + product_ext;
        end
    end

endmodule

codefest/cf04/hdl/mac_tb.v
// mac_tb.v — Testbench for mac_correct.v
// Sequence: a=3,b=4 for 3 cycles → rst → a=-5,b=2 for 2 cycles

`timescale 1ns/1ps

module mac_tb;
    logic        clk, rst;
    logic signed [7:0]  a, b;
    logic signed [31:0] out;

    mac dut (.clk(clk), .rst(rst), .a(a), .b(b), .out(out));

    // 10 ns clock
    initial clk = 0;
    always #5 clk = ~clk;

    task check(input signed [31:0] expected, input string label);
        @(posedge clk); #1;
        if (out !== expected) begin
            $display("FAIL [%s]: got %0d, expected %0d", label, out, expected);
            $finish;
        end else
            $display("PASS [%s]: out = %0d", label, out);
    endtask

    initial begin
        $dumpfile("dump.vcd");
        $dumpvars(0, mac_tb);

        rst = 1; a = 0; b = 0;
        @(posedge clk); #1;
        rst = 0;

        // Cycle 1-3: a=3, b=4 → product=12 each cycle
        a = 3; b = 4;
        check(12,  "cycle1 (3*4=12)");
        check(24,  "cycle2 (12+12=24)");
        check(36,  "cycle3 (24+12=36)");

        // Assert reset
        rst = 1;
        @(posedge clk); #1;
        if (out !== 0) begin
            $display("FAIL [rst]: out = %0d, expected 0", out);
            $finish;
        end else
            $display("PASS [rst]: out = 0");
        rst = 0;

        // Cycle 4-5: a=-5, b=2 → product=-10 each cycle
        a = -5; b = 2;
        check(-10, "cycle4 (-5*2=-10)");
        check(-20, "cycle5 (-10+(-10)=-20)");

        $display("All tests PASSED");
        $finish;
    end
endmodule

codefest/cf04/CLLM_Logs/dump.vcd
$date
	Sun Apr 26 20:59:16 2026
$end
$version
	Icarus Verilog
$end
$timescale
	1ps
$end
$scope module mac_tb $end
$var wire 32 ! out [31:0] $end
$var reg 8 " a [7:0] $end
$var reg 8 # b [7:0] $end
$var reg 1 $ clk $end
$var reg 1 % rst $end
$scope module dut $end
$var wire 8 & a [7:0] $end
$var wire 8 ' b [7:0] $end
$var wire 1 $ clk $end
$var wire 1 % rst $end
$var reg 32 ( out [31:0] $end
$var reg 16 ) product [15:0] $end
$var reg 32 * product_ext [31:0] $end
$upscope $end
$scope task check $end
$var reg 32 + expected [31:0] $end
$upscope $end
$upscope $end
$enddefinitions $end
#0
$dumpvars
bx +
bx *
bx )
bx (
b0 '
b0 &
1%
0$
b0 #
b0 "
bx !
$end
#5000
b0 !
b0 (
1$
#6000
b1100 +
b100 #
b100 '
b11 "
b11 &
0%
#10000
0$
#15000
b1100 !
b1100 (
b1100 *
b1100 )
1$
#16000
b11000 +
#20000
0$
#25000
b11000 !
b11000 (
1$
#26000
b100100 +
#30000
0$
#35000
b100100 !
b100100 (
1$
#36000
1%
#40000
0$
#45000
b0 !
b0 (
1$
#46000
b11111111111111111111111111110110 +
b10 #
b10 '
b11111011 "
b11111011 &
0%
#50000
0$
#55000
b11111111111111111111111111110110 !
b11111111111111111111111111110110 (
b11111111111111111111111111110110 *
b1111111111110110 )
1$
#56000
b11111111111111111111111111101100 +
#60000
0$
#65000
b11111111111111111111111111101100 !
b11111111111111111111111111101100 (
1$
